data_morph/__init__.py
data_morph/__main__.py
data_morph/cli.py
data_morph/morpher.py
data_morph/progress.py
data_morph/bounds/__init__.py
data_morph/bounds/_utils.py
data_morph/bounds/bounding_box.py
data_morph/bounds/interval.py
data_morph/data/__init__.py
data_morph/data/dataset.py
data_morph/data/loader.py
data_morph/data/stats.py
data_morph/data/starter_shapes/bunny.csv
data_morph/data/starter_shapes/cat.csv
data_morph/data/starter_shapes/dino.csv
data_morph/data/starter_shapes/dog.csv
data_morph/data/starter_shapes/gorilla.csv
data_morph/data/starter_shapes/music.csv
data_morph/data/starter_shapes/panda.csv
data_morph/data/starter_shapes/pi.csv
data_morph/data/starter_shapes/python.csv
data_morph/data/starter_shapes/sheep.csv
data_morph/data/starter_shapes/soccer_ball.csv
data_morph/data/starter_shapes/superdatascience.csv
data_morph/plotting/__init__.py
data_morph/plotting/animation.py
data_morph/plotting/static.py
data_morph/plotting/style.py
data_morph/plotting/config/plot_style.mplstyle
data_morph/shapes/__init__.py
data_morph/shapes/factory.py
data_morph/shapes/bases/__init__.py
data_morph/shapes/bases/line_collection.py
data_morph/shapes/bases/point_collection.py
data_morph/shapes/bases/shape.py
data_morph/shapes/circles/__init__.py
data_morph/shapes/circles/bullseye.py
data_morph/shapes/circles/circle.py
data_morph/shapes/circles/rings.py
data_morph/shapes/lines/__init__.py
data_morph/shapes/lines/diamond.py
data_morph/shapes/lines/high_lines.py
data_morph/shapes/lines/horizontal_lines.py
data_morph/shapes/lines/rectangle.py
data_morph/shapes/lines/slant_down.py
data_morph/shapes/lines/slant_up.py
data_morph/shapes/lines/star.py
data_morph/shapes/lines/vertical_lines.py
data_morph/shapes/lines/wide_lines.py
data_morph/shapes/lines/x_lines.py
data_morph/shapes/points/__init__.py
data_morph/shapes/points/club.py
data_morph/shapes/points/dots_grid.py
data_morph/shapes/points/figure_eight.py
data_morph/shapes/points/heart.py
data_morph_ai-0.3.1.dist-info/LICENSE
data_morph_ai-0.3.1.dist-info/METADATA
data_morph_ai-0.3.1.dist-info/WHEEL
data_morph_ai-0.3.1.dist-info/entry_points.txt
data_morph_ai-0.3.1.dist-info/top_level.txt
data_morph_ai-0.3.1.dist-info/RECORD
