Metadata-Version: 2.2
Name: data-morph-ai
Version: 0.3.1
Summary: Teaching tool on the importance of data visualization.
Author-email: Stefanie Molin <data-morph@stefaniemolin.com>, Aaron Stevens <bheklilr2@gmail.com>, Justin Matejka <Justin.Matejka@Autodesk.com>
Maintainer: Stefanie Molin
License: MIT License
Project-URL: Bug Tracker, https://github.com/stefmolin/data-morph/issues
Project-URL: Documentation, https://stefaniemolin.com/data-morph/stable/api.html
Project-URL: Homepage, https://stefaniemolin.com/data-morph
Project-URL: Source, https://github.com/stefmolin/data-morph
Keywords: data animation,data visualization,summary statistics
Classifier: Development Status :: 4 - Beta
Classifier: Framework :: Matplotlib
Classifier: Intended Audience :: Education
Classifier: Operating System :: OS Independent
Classifier: Programming Language :: Python :: 3 :: Only
Classifier: Programming Language :: Python :: 3.9
Classifier: Programming Language :: Python :: 3.10
Classifier: Programming Language :: Python :: 3.11
Classifier: Programming Language :: Python :: 3.12
Classifier: Programming Language :: Python :: 3.13
Classifier: Topic :: Scientific/Engineering :: Artificial Intelligence
Classifier: Topic :: Scientific/Engineering :: Visualization
Requires-Python: >=3.9
License-File: LICENSE
Requires-Dist: matplotlib>=3.7
Requires-Dist: numpy>=1.20
Requires-Dist: pandas>=1.2
Requires-Dist: rich>=13.9.4
Provides-Extra: dev
Requires-Dist: pre-commit; extra == "dev"
Requires-Dist: pytest; extra == "dev"
Requires-Dist: pytest-cov; extra == "dev"
Requires-Dist: pytest-mock; extra == "dev"
Requires-Dist: pytest-randomly; extra == "dev"
Requires-Dist: pytest-xdist; extra == "dev"
Provides-Extra: docs
Requires-Dist: pydata-sphinx-theme>=0.15.3; extra == "docs"
Requires-Dist: sphinx>=7.2.6; extra == "docs"
Requires-Dist: sphinx-argparse-cli>=1.16.0; extra == "docs"
Requires-Dist: sphinx-copybutton>=0.5.1; extra == "docs"
Requires-Dist: sphinx-design>=0.6.1; extra == "docs"
